pinnsjax
